Metadata-Version: 1.1
Name: wmicq
Version: 1.0.0
Summary: Simple  wrapper for wmic Windows command allowing to query Windows Management Instrumentation (WMI)
Home-page: https://pypi.python.org/pypi/wmicq
Author: baseIT
Author-email: baseit.app+wmicq@gmail.com
License: MIT
Download-URL: https://pypi.python.org/pypi/wmicq
Keywords: WMI wmic
Platform: UNKNOWN
Classifier: Development Status :: 4 - Beta
Classifier: License :: OSI Approved :: MIT License
Classifier: Programming Language :: Python :: 3
Classifier: Programming Language :: Python :: 3.4
Classifier: Programming Language :: Python :: 3.5
Classifier: Intended Audience :: Developers
Classifier: Intended Audience :: Information Technology
Classifier: Intended Audience :: System Administrators
Classifier: Operating System :: Microsoft :: Windows
